setup.py
wordmatrix/__init__.py
wordmatrix.egg-info/PKG-INFO
wordmatrix.egg-info/SOURCES.txt
wordmatrix.egg-info/dependency_links.txt
wordmatrix.egg-info/top_level.txt