Metadata-Version: 1.1
Name: wordmatrix
Version: 0.0.1
Summary: A Python-based simple search
Home-page: UNKNOWN
Author: Ikuya Yamada
Author-email: ikuya@ousia.jp
License: Copyright 2018 Studio Ousia
